kybernet/__init__.py
kybernet/client.py
kybernet/exceptions.py
kybernet-0.0.3.dist-info/LICENSE
kybernet-0.0.3.dist-info/METADATA
kybernet-0.0.3.dist-info/WHEEL
kybernet-0.0.3.dist-info/top_level.txt
kybernet-0.0.3.dist-info/RECORD
