Metadata-Version: 2.1
Name: kybernet
Version: 0.0.3
Summary: Unofficial python wrapper for Kyber Network API.
Home-page: https://github.com/dave-lanigan/kyber-api-python
Author: Daithi
Author-email: dav.lanigan@gmail.com
License: UNKNOWN
Platform: UNKNOWN
Classifier: Development Status :: 2 - Pre-Alpha
Classifier: Programming Language :: Python :: 3
Classifier: License :: OSI Approved :: MIT License
Requires-Python: >=3.6
Requires-Dist: requests
Provides-Extra: dev
Requires-Dist: pytest (>=3.5) ; extra == 'dev'
